Workbook

Sheet Control de Facturas
A1: CONTROL DE FACTURAS Y COBROS — FREELANCE
A2: AutónomoLab — autonomolab.com | Celdas naranjas = editables | Celdas verdes = cobradas
A4: 📊 RESUMEN RÁPIDO
A5: Total facturado: | B5: =SUMIF(L8:L200,"Cobrada",G8:G200)+SUMIF(L8:L200,"Pendiente",G8:G200)+SUMIF(L8:L200,"Vencida",G8:G200)
A6: Cobrado: | B6: =SUMIF(L8:L200,"Cobrada",G8:G200)
A7: Fecha | B7: Nº Factura | C7: Cliente | D7: Concepto | E7: Base € | F7: IVA € | G7: TOTAL € | H7: Fecha límite | I7: Fecha cobro | J7: Días | K7: Método pago | L7: Estado
A8: Vencido sin cobrar: | B8: =SUMIF(L8:L200,"Vencida",G8:G200) | G8: =IF(E8="","",E8+F8) | J8: =IF(OR(I8="",I8=0),IF(OR(H8="",H8=0),"",TODAY()-H8),I8-H8) | L8: Pendiente
A9: Nº facturas total: | B9: =COUNTA(B8:B200) | G9: =IF(E9="","",E9+F9) | J9: =IF(OR(I9="",I9=0),IF(OR(H9="",H9=0),"",TODAY()-H9),I9-H9) | L9: Pendiente
A10: Nº facturas cobradas: | B10: =COUNTIF(L8:L200,"Cobrada") | G10: =IF(E10="","",E10+F10) | J10: =IF(OR(I10="",I10=0),IF(OR(H10="",H10=0),"",TODAY()-H10),I10-H10) | L10: Pendiente
G11: =IF(E11="","",E11+F11) | J11: =IF(OR(I11="",I11=0),IF(OR(H11="",H11=0),"",TODAY()-H11),I11-H11) | L11: Pendiente
G12: =IF(E12="","",E12+F12) | J12: =IF(OR(I12="",I12=0),IF(OR(H12="",H12=0),"",TODAY()-H12),I12-H12) | L12: Pendiente
G13: =IF(E13="","",E13+F13) | J13: =IF(OR(I13="",I13=0),IF(OR(H13="",H13=0),"",TODAY()-H13),I13-H13) | L13: Pendiente
G14: =IF(E14="","",E14+F14) | J14: =IF(OR(I14="",I14=0),IF(OR(H14="",H14=0),"",TODAY()-H14),I14-H14) | L14: Pendiente
G15: =IF(E15="","",E15+F15) | J15: =IF(OR(I15="",I15=0),IF(OR(H15="",H15=0),"",TODAY()-H15),I15-H15) | L15: Pendiente
G16: =IF(E16="","",E16+F16) | J16: =IF(OR(I16="",I16=0),IF(OR(H16="",H16=0),"",TODAY()-H16),I16-H16) | L16: Pendiente
G17: =IF(E17="","",E17+F17) | J17: =IF(OR(I17="",I17=0),IF(OR(H17="",H17=0),"",TODAY()-H17),I17-H17) | L17: Pendiente
G18: =IF(E18="","",E18+F18) | J18: =IF(OR(I18="",I18=0),IF(OR(H18="",H18=0),"",TODAY()-H18),I18-H18) | L18: Pendiente
G19: =IF(E19="","",E19+F19) | J19: =IF(OR(I19="",I19=0),IF(OR(H19="",H19=0),"",TODAY()-H19),I19-H19) | L19: Pendiente
G20: =IF(E20="","",E20+F20) | J20: =IF(OR(I20="",I20=0),IF(OR(H20="",H20=0),"",TODAY()-H20),I20-H20) | L20: Pendiente
G21: =IF(E21="","",E21+F21) | J21: =IF(OR(I21="",I21=0),IF(OR(H21="",H21=0),"",TODAY()-H21),I21-H21) | L21: Pendiente
G22: =IF(E22="","",E22+F22) | J22: =IF(OR(I22="",I22=0),IF(OR(H22="",H22=0),"",TODAY()-H22),I22-H22) | L22: Pendiente
... G57: =IF(E57="","",E57+F57) | J57: =IF(OR(I57="",I57=0),IF(OR(H57="",H57=0),"",TODAY()-H57),I57-H57) | L57: Pendiente
A59: LEYENDA DE ESTADOS
A60: Pendiente | B60: Emitida y dentro del plazo de pago
A61: Cobrada | B61: Cobro confirmado
A62: Vencida | B62: Superado el plazo sin cobrar
A63: Borrador | B63: Preparada pero no enviada
A64: Anulada | B64: Factura anulada con rectificativa

Sheet Clientes
A1: BASE DE DATOS DE CLIENTES
A3: Empresa/Nombre | B3: NIF/CIF | C3: Email | D3: Teléfono | E3: Dirección | F3: Condiciones pago | G3: Facturado total | H3: Notas
G4: =SUMIF('Control de Facturas'!C$8:C$57,A4,'Control de Facturas'!G$8:G$57)
G5: =SUMIF('Control de Facturas'!C$8:C$57,A5,'Control de Facturas'!G$8:G$57)
G6: =SUMIF('Control de Facturas'!C$8:C$57,A6,'Control de Facturas'!G$8:G$57)
G7: =SUMIF('Control de Facturas'!C$8:C$57,A7,'Control de Facturas'!G$8:G$57)
G8: =SUMIF('Control de Facturas'!C$8:C$57,A8,'Control de Facturas'!G$8:G$57)
G9: =SUMIF('Control de Facturas'!C$8:C$57,A9,'Control de Facturas'!G$8:G$57)
G10: =SUMIF('Control de Facturas'!C$8:C$57,A10,'Control de Facturas'!G$8:G$57)
G11: =SUMIF('Control de Facturas'!C$8:C$57,A11,'Control de Facturas'!G$8:G$57)
G12: =SUMIF('Control de Facturas'!C$8:C$57,A12,'Control de Facturas'!G$8:G$57)
G13: =SUMIF('Control de Facturas'!C$8:C$57,A13,'Control de Facturas'!G$8:G$57)
G14: =SUMIF('Control de Facturas'!C$8:C$57,A14,'Control de Facturas'!G$8:G$57)
G15: =SUMIF('Control de Facturas'!C$8:C$57,A15,'Control de Facturas'!G$8:G$57)
... G29: =SUMIF('Control de Facturas'!C$8:C$57,A29,'Control de Facturas'!G$8:G$57)

Sheet Instrucciones
A1: CÓMO USAR ESTA PLANTILLA
A3: 📋 PESTAÑA CONTROL DE FACTURAS
A4: 1. Por cada factura que emitas, añade una fila nueva.
A5: 2. Introduce: fecha, número de factura, cliente, concepto, base e IVA.
A6: 3. El Total se calcula automáticamente (Base + IVA).
A7: 4. Pon la fecha límite de cobro (plazo acordado con el cliente).
A8: 5. Cuando cobres, pon la fecha de cobro y cambia el Estado a 'Cobrada'.
A9: 6. El resumen rápido te muestra en tiempo real lo cobrado y lo pendiente.
A11: 👥 PESTAÑA CLIENTES
A12: • Guarda aquí los datos fiscales de tus clientes habituales.
A13: • La columna 'Facturado total' suma automáticamente todas sus facturas.
A14: • Útil para saber qué clientes generan más ingresos.
... A22: 🌐 Más herramientas gratuitas en autonomolab.com
